pybengali/__init__.py
pybengali-0.0.1.dist-info/LICENSE
pybengali-0.0.1.dist-info/METADATA
pybengali-0.0.1.dist-info/WHEEL
pybengali-0.0.1.dist-info/top_level.txt
pybengali-0.0.1.dist-info/RECORD
