Metadata-Version: 2.1
Name: pybengali
Version: 0.0.1
Summary: pybengali is a python3 package for Bengali DateTime and Bengali numeric number conversation and many more
Home-page: https://github.com/pyshawon/pybengali
Author: Shaid Hasan Shawon
Author-email: pyshawon@gmail.com
License: MIT
Keywords: pybengali,bengali,bangla,bangla date,bangla digit,python bangla,python package,python bangla package,python bengali,python bengali date,django bangla date,django bangla,django bengali
Platform: UNKNOWN
Classifier: Operating System :: OS Independent
Classifier: Programming Language :: Python :: 3.6
Classifier: Programming Language :: Python :: 3.7
Classifier: Programming Language :: Python :: 3.8
Classifier: Programming Language :: Python :: 3.9
Classifier: Intended Audience :: Developers
Classifier: License :: OSI Approved :: MIT License
Classifier: Development Status :: 5 - Production/Stable
Classifier: Topic :: Software Development :: Libraries :: Python Modules
Requires-Python: >=3.6
